sankey_cashflow/__init__.py
sankey_cashflow/sankey_cash.py
sankey_cash-0.2.1.dist-info/LICENSE
sankey_cash-0.2.1.dist-info/METADATA
sankey_cash-0.2.1.dist-info/WHEEL
sankey_cash-0.2.1.dist-info/top_level.txt
sankey_cash-0.2.1.dist-info/RECORD
