Metadata-Version: 2.1
Name: sankey-cash
Version: 0.2.1
Summary: Some classes for generating cashflow sankey diagrams
Author: Paul Marcontell
Author-email: Paul Marcontell <paul.marcontell@gmail.com>
License: MIT License
Project-URL: Homepage, https://github.com/paulkm/sankey-cash
Project-URL: Bug Tracker, https://github.com/paulkm/sankey-cash/issues
Classifier: Programming Language :: Python :: 3
Classifier: License :: OSI Approved :: MIT License
Classifier: Operating System :: OS Independent
Requires-Python: >=3.7
License-File: LICENSE
Requires-Dist: pygsheets ~=2.0
Requires-Dist: pandas ~=1.5
Requires-Dist: plotly ~=5.11
Requires-Dist: numpy ~=1.24
Requires-Dist: networkx ~=2.8
